hacs_auth/__init__.py
hacs_auth/actor.py
hacs_auth/audit.py
hacs_auth/auth_manager.py
hacs_auth/decorators.py
hacs_auth/permissions.py
hacs_auth/secure_logging.py
hacs_auth/secure_tools.py
hacs_auth/security.py
hacs_auth/session.py
hacs_auth/threat_detection.py
hacs_auth/tool_security.py
hacs_auth-0.4.3.dist-info/METADATA
hacs_auth-0.4.3.dist-info/WHEEL
hacs_auth-0.4.3.dist-info/RECORD
